odoo/addons/l10n_ar_ledger/README.rst
odoo/addons/l10n_ar_ledger/__init__.py
odoo/addons/l10n_ar_ledger/__manifest__.py
odoo/addons/l10n_ar_ledger/i18n/es_AR.po
odoo/addons/l10n_ar_ledger/i18n/l10n_ar_ledger.pot
odoo/addons/l10n_ar_ledger/models/__init__.py
odoo/addons/l10n_ar_ledger/models/account_vat_ledger.py
odoo/addons/l10n_ar_ledger/models/account_vat_ledger_xlsx.py
odoo/addons/l10n_ar_ledger/models/l10n_latam_document_type.py
odoo/addons/l10n_ar_ledger/readme/CONTRIBUTORS.rst
odoo/addons/l10n_ar_ledger/readme/DESCRIPTION.rst
odoo/addons/l10n_ar_ledger/readme/HISTORY.rst
odoo/addons/l10n_ar_ledger/readme/ROADMAP.rst
odoo/addons/l10n_ar_ledger/security/ir.model.access.csv
odoo/addons/l10n_ar_ledger/security/security.xml
odoo/addons/l10n_ar_ledger/static/description/icon.png
odoo/addons/l10n_ar_ledger/static/description/index.html
odoo/addons/l10n_ar_ledger/views/account_vat_ledger.xml
odoo/addons/l10n_ar_ledger/views/account_vat_ledger_pdf.xml
odoo/addons/l10n_ar_ledger/views/account_vat_ledger_xlsx.xml
odoo14_addon_l10n_ar_ledger-14.0.0.0.3.dist-info/METADATA
odoo14_addon_l10n_ar_ledger-14.0.0.0.3.dist-info/WHEEL
odoo14_addon_l10n_ar_ledger-14.0.0.0.3.dist-info/top_level.txt
odoo14_addon_l10n_ar_ledger-14.0.0.0.3.dist-info/RECORD
